hilbert_modgroup/__init__.py
hilbert_modgroup/all.py
hilbert_modgroup/hilbert_modular_group_class.py
hilbert_modgroup/hilbert_modular_group_element.cpython-312-darwin.so
hilbert_modgroup/hilbert_modular_group_element.pyx
hilbert_modgroup/pullback.py
hilbert_modgroup/pullback_cython.cpython-312-darwin.so
hilbert_modgroup/pullback_cython.pyx
hilbert_modgroup/upper_half_plane.cpython-312-darwin.so
hilbert_modgroup/upper_half_plane.pxd
hilbert_modgroup/upper_half_plane.pyx
hilbert_modgroup/utils.py
hilbert_modgroup/version.py
hilbert_modular_group-0.1.3.dist-info/licenses/LICENSE
hilbert_modular_group-0.1.3.dist-info/METADATA
hilbert_modular_group-0.1.3.dist-info/WHEEL
hilbert_modular_group-0.1.3.dist-info/top_level.txt
hilbert_modular_group-0.1.3.dist-info/RECORD
