Metadata-Version: 2.4
Name: hilbert_modular_group
Version: 0.1.3
Summary: Algorithms for Hilbert modular groups
Author-email: Fredrik Stromberg <fredrik314@gmail.com>
License:                     GNU GENERAL PUBLIC LICENSE
Project-URL: homepage, https://github.com/fredstro/hilbertmodgroup
Project-URL: bugtracker, https://github.com/fredstro/hilbertmodgroup/issues
Project-URL: sourcecode, https://github.com/fredstro/hilbertmodgroup/
Keywords: hilbert modular groups,reduction algorithms
Classifier: Development Status :: 4 - Beta
Classifier: Intended Audience :: Science/Research
Classifier: License :: OSI Approved :: GNU General Public License v3 or later (GPLv3+)
Classifier: Operating System :: OS Independent
Classifier: Programming Language :: C
Classifier: Programming Language :: C++
Classifier: Programming Language :: Python
Classifier: Programming Language :: Cython
Classifier: Topic :: Scientific/Engineering :: Mathematics
License-File: LICENSE
Requires-Dist: passagemath-standard
Requires-Dist: passagemath-plot
Dynamic: license-file
